{
  "Standard": {
    "checked": true,
    "traces": { "744": "Internal Standard" },
    "window": [0, 70]
  },
  "brGDGTs": {
    "checked": true,
    "traces": {
      "1050": "IIIa, IIIa'', IIIa'",
      "1048": "IIIb, IIIb'",
      "1046": "IIIc, IIIc'",
      "1036": "IIa, IIa'",
      "1034": "IIb, IIb'",
      "1032": "IIc, IIc'",
      "1022": "Ia",
      "1020": "Ib",
      "1018": "Ic"
    },
    "window": [20, 40]
  },
  "isoGDGTs": {
    "checked": true,
    "traces": {
      "1302": "GDGT-0",
      "1300": "GDGT-1",
      "1298": "GDGT-2",
      "1296": "GDGT-3",
      "1292": "GDGT-4, GDGT-4'"
    },
    "window": [5, 25]
  },
  "OH-GDGTs": {
    "checked": true,
    "traces": {
      "1300": "OH-GDGT-0",
      "1298": "OH-GDGT-1, 2OH-GDGT-0",
      "1296": "OH-GDGT-2"
    },
    "window": [35, 50]
  }
}
